linelib/__init__.py
linelib/const.py
linelib/database.py
linelib/errors.py
linelib/logger.py
linelib/tools.py
linelib/http/__init__.py
linelib/http/fetch.py
linelib/http/portal.py
linelib/http/webhook.py
linelib/models/__init__.py
linelib/models/message.py
linelib/models/new.py
linelib/models/types.py
linelib-0.1.dist-info/LICENSE
linelib-0.1.dist-info/METADATA
linelib-0.1.dist-info/WHEEL
linelib-0.1.dist-info/top_level.txt
linelib-0.1.dist-info/RECORD
