Metadata-Version: 2.1
Name: linelib
Version: 0.1
Summary: Launch your LINE bot to the next level.
Home-page: https://github.com/AWeirdScratcher/linelib
Author: AWeirdScratcher
Author-email: aweirdscrather@gmail.com
License: MIT
Keywords: line,bot,line bot,sdk
Classifier: Programming Language :: Python :: 3
Classifier: License :: OSI Approved :: MIT License
Classifier: Operating System :: OS Independent
License-File: LICENSE
Requires-Dist: requests
Requires-Dist: flask
